{
  "$schema": "http://json-schema.org/draft-07/schema#",
  "$id": "http://example.com/IndividualHumanMetadataTemplate",
  "title": "IndividualHumanMetadataTemplate",
  "type": "object",
  "properties": {
    "ethnicity": {},
    "sex": {
      "enum": [
        "female",
        "missing or unknown",
        "male"
      ]
    },
    "diagnosisCriteria": {},
    "diabetes": {
      "enum": [
        "type 1",
        "remote/inactive",
        "Absent",
        "other type",
        "type 2",
        "unknown",
        "other",
        "not assessed or unknown",
        "recent/active",
        ""
      ]
    },
    "pH": {},
    "diagnosis": {
      "enum": [
        "Lung Cancer",
        "dystonia",
        "Juvenile Myelomonocytic Leukemia",
        "Substance Related Disorder",
        "Williams Syndrome",
        "Major Depressive Disorder",
        "Not Applicable",
        "Control",
        "Alzheimer disease with psychosis",
        "MCI-DS",
        "type 2 diabetes mellitus",
        "Posterior Cortical Atrophy",
        "Colon Cancer",
        "Dyslipidemia",
        "traumatic brain injury",
        "Parkinson's disease",
        "mild cognitive impairment",
        "Bladder Cancer",
        "vascular dementia",
        "AD-DS",
        "Neurofibromatosis 2",
        "Cardiovascular Disease",
        "Lewy body disease",
        "Pancreatic Cancer",
        "progressive supranuclear palsy",
        "no cognitive impairment",
        "Subjective Memory Concern",
        "essential tremor",
        "Brain Cancer",
        "hypertension",
        "Prostate Cancer",
        "corticobasal degeneration disorder",
        "dementia",
        "Metabolic Syndrome",
        "obesity",
        "Skin Cancer",
        "Autism Spectrum Disorder",
        "CS-DS",
        "unknown",
        "anxiety",
        "Breast Cancer",
        "Ovary Cancer",
        "pathological aging",
        "Neurofibromatosis 1",
        "Schizophrenia",
        "Alzheimer Disease",
        "Tourette Syndrome",
        "hypoxia",
        "multiple system atrophy",
        "amyotrophic lateral sclerosis",
        "Affective Disorder",
        "Fibrocystic Breast Disease",
        "gliosis",
        "obsessive compulsive disorder",
        "Bipolar Disorder",
        "Leukemia",
        "other",
        "Cervical Cancer",
        "frontotemporal dementia",
        ""
      ]
    },
    "individualID": {
      "not": {
        "type": "null"
      },
      "minLength": 1
    },
    "causeDeath": {},
    "CERAD": {
      "enum": [
        "No AD C0",
        "Moderate Probable C2",
        "missing or unknown",
        "Frequent Definite C3",
        "Sparse Possible C1",
        ""
      ]
    },
    "race": {
      "enum": [
        "Black or African American",
        "Asian",
        "Native Hawaiian or Other Pacific Islander",
        "American Indian or Alaska Native",
        "White",
        ""
      ]
    },
    "Braak": {
      "enum": [
        "No BRAAK stage",
        "BRAAK Stage 2",
        "BRAAK Stage 1",
        "BRAAK Stage 3",
        "BRAAK Stage 5",
        "BRAAK Stage 4",
        "missing or unknown",
        "BRAAK Stage 6",
        ""
      ]
    },
    "mannerDeath": {
      "enum": [
        "natural causes",
        "suicide",
        "homicide",
        "undetermined",
        "accident",
        ""
      ]
    },
    "Component": {},
    "dataContributionGroup": {
      "enum": [
        "ADNI",
        "MC ADRC",
        "MCBB",
        "Knight ADRC",
        "Baker Heart & Diabetes Institute",
        "Duke",
        "MCSA",
        "IADRC",
        "Emory",
        ""
      ]
    },
    "individualIdSource": {
      "enum": [
        "TAA",
        "Clotomics_PAIKEA_MSSM",
        "AIBS",
        "Einstein",
        "NYBB",
        "Newcastle",
        "Pritzker",
        "Oxford",
        "Washington University",
        "Emory",
        "JAX",
        "UCSF",
        "BEB_Miller",
        "HBSFRC",
        "IU",
        "UCI_TMF",
        "UM-BTB",
        "LIBD",
        "SMRI",
        "ABR",
        "ABN",
        "DongLab",
        "Caltech",
        "ADNI",
        "PGP",
        "Pitt",
        "LivingBrainProject_MSSM",
        "University of Florida",
        "NIMH-HBCC",
        "NICHD",
        "MayoBrainBank",
        "NDRI",
        "Sestan",
        "University of Miami",
        "Penn",
        "UW-CDL",
        "MSSM",
        "StemExpress",
        "XCell Science",
        "Geschwind",
        "Mayo Clinic",
        "Novogenix",
        "Rush",
        "Yale",
        "Michigan University",
        "BannerSun",
        "Vaccarino",
        "HBTRC",
        ""
      ]
    },
    "hypertension": {
      "enum": [
        "remote/inactive",
        "Absent",
        "no",
        "unknown",
        "yes",
        "not assessed or unknown",
        "recent/active",
        ""
      ]
    },
    "yearsEducation": {},
    "cohort": {
      "enum": [
        "LBP",
        "MCR",
        "NYBB",
        "MARS",
        "Biggs Institute Brain Bank",
        "1Florida ADRC (1FL ADRC)",
        "DiCAD",
        "BLSA",
        "Framingham",
        "Mayo Clinic ADRC (Mayo ADRC)",
        "MCJ",
        "UW ADRC",
        "MIND",
        "MARS-WI",
        "UPenn",
        "ACT",
        "Indiana ADRC (IADRC)",
        "Michigan ADRC (MADC)",
        "SMRI",
        "HUP",
        "UK Biobank",
        "EFIGA",
        "ADRC",
        "Emory_ADRC",
        "Banner",
        "ADNI",
        "RADC",
        "CHDWB",
        "MC",
        "POINTER",
        "Pitt ADRC",
        "Tulsa LIBR-1000",
        "WHICAP",
        "HBCC",
        "FBS",
        "BEB-Miller",
        "EHBS",
        "BEAM",
        "CLINCOR",
        "HPGP",
        "Knight ADRC",
        "ABC-DS",
        "ROSMAP",
        "Mayo Clinic Brain Bank (MCBB)",
        "MSBB",
        "Columbia ADRC",
        "Mayo Clinic Study of Aging (MCSA)",
        "UPBB",
        "UFL",
        "HBTRC",
        ""
      ]
    },
    "species": {
      "enum": [
        "Rhesus macaque",
        "Drosophila melanogaster",
        "Human",
        "Mouse",
        "Pan troglodytes",
        "Sus scrofa",
        "Gallus gallus",
        "Rat"
      ]
    },
    "pmiUnits": {
      "enum": [
        "hours",
        "minutes",
        ""
      ]
    },
    "brainWeight": {},
    "ageDeath": {},
    "height": {},
    "weight": {},
    "PMI": {},
    "apoe4Status": {
      "enum": [
        "no E4",
        "missing or unknown",
        "one or two E4",
        ""
      ]
    },
    "ageDeathUnits": {
      "enum": [
        "gestational weeks",
        "weeks",
        "PCW",
        "years",
        "days",
        "months",
        ""
      ]
    },
    "hypercholesterolemia": {},
    "apoeGenotype": {
      "enum": [
        "33",
        "24",
        "34",
        "22",
        "44",
        "23",
        ""
      ]
    }
  },
  "required": [
    "sex",
    "individualID",
    "species"
  ]
}